template_toolpackage/__init__.py
template_toolpackage/functions.py
template_toolpackage/version.py
template_toolpackage-0.0.4.dist-info/METADATA
template_toolpackage-0.0.4.dist-info/WHEEL
template_toolpackage-0.0.4.dist-info/top_level.txt
template_toolpackage-0.0.4.dist-info/RECORD
