Metadata-Version: 2.1
Name: template-toolpackage
Version: 0.0.4
Summary: UNKNOWN
Home-page: UNKNOWN
License: UNKNOWN
Platform: UNKNOWN
Requires-Python: >=3.9.4
Requires-Dist: pandas
Requires-Dist: numpy
